MANIFEST.in
README.md
UNLICENSE
distribute_setup.py
setup.py
src/djclsview.py
src/django_clsview.egg-info/PKG-INFO
src/django_clsview.egg-info/SOURCES.txt
src/django_clsview.egg-info/dependency_links.txt
src/django_clsview.egg-info/top_level.txt