Metadata-Version: 1.0
Name: django-clsview
Version: 0.0.2
Summary: Yet another class-based view system for Django.
Home-page: http://github.com/zacharyvoase/django-clsview
Author: Zachary Voase
Author-email: z@zacharyvoase.com
License: UNKNOWN
Platform: UNKNOWN
